[
    {
        "place": "London",
        "id": 1,
        "flag": 1,
        "rent": true,
        "sale": false,
        "location": "Rhyme Time at St John's Wood Library",
        "buildingname": "Great House",
        "noofroom": 4,
        "noofbed": 3,
        "noofbath": 2,
        "sft": 1000,
        "pricepermonth": 1000,
        "img": "/src/assets/1.jpg",
        "popular": false
    },
    {
        "place": "London",
        "id": 2,
        "flag": 1,
        "rent": true,
        "sale": false,
        "location": "Central London",
        "buildingname": "Luxury Apartments",
        "noofroom": 3,
        "noofbed": 2,
        "noofbath": 2,
        "sft": 1200,
        "pricepermonth": 1500,
        "img": "/src/assets/2.jpg",
        "popular": true
    },
    {
        "place": "London",
        "id": 3,
        "flag": 1,
        "rent": true,
        "sale": false,
        "location": "Kensington Gardens",
        "buildingname": "Cozy Studio",
        "noofroom": 2,
        "noofbed": 1,
        "noofbath": 1,
        "sft": 600,
        "pricepermonth": 800,
        "img": "/src/assets/3.jpg",
        "popular": false
    },
    {
        "place": "London",
        "id": 4,
        "flag": 1,
        "rent": false,
        "sale": true,
        "location": "Camden Town",
        "buildingname": "Townhouse",
        "noofroom": 5,
        "noofbed": 4,
        "noofbath": 3,
        "sft": 1800,
        "pricepermonth": 2200,
        "img": "/src/assets/4.jpg",
        "popular": true
    },
    {
        "place": "London",
        "id": 5,
        "flag": 1,
        "rent": false,
        "sale": true,
        "location": "Notting Hill",
        "buildingname": "Charming Cottage",
        "noofroom": 2,
        "noofbed": 1,
        "noofbath": 1,
        "sft": 800,
        "pricepermonth": 1100,
        "img": "/src/assets/5.jpg",
        "popular": false
    },
    {
        "place": "London",
        "id": 6,
        "flag": 1,
        "rent": true,
        "sale": false,
        "location": "Shoreditch",
        "buildingname": "Loft Apartment",
        "noofroom": 3,
        "noofbed": 2,
        "noofbath": 2,
        "sft": 1000,
        "pricepermonth": 1300,
        "img": "/src/assets/6.jpg",
        "popular": false
    },
    {
        "place": "London",
        "id": 7,
        "flag": 1,
        "rent": false,
        "sale": true,
        "location": "Westminster",
        "buildingname": "Penthouse Suite",
        "noofroom": 4,
        "noofbed": 3,
        "noofbath": 2,
        "sft": 1500,
        "pricepermonth": 2500,
        "img": "/src/assets/7.jpg",
        "popular": true
    },
    {
        "place": "London",
        "id": 8,
        "flag": 1,
        "rent": true,
        "sale": false,
        "location": "Covent Garden",
        "buildingname": "Modern Condo",
        "noofroom": 2,
        "noofbed": 1,
        "noofbath": 1,
        "sft": 700,
        "pricepermonth": 900,
        "img": "/src/assets/8.jpg",
        "popular": false
    },
    {
        "place": "London",
        "id": 9,
        "flag": 1,
        "rent": false,
        "sale": true,
        "location": "Greenwich",
        "buildingname": "Riverside Villa",
        "noofroom": 6,
        "noofbed": 4,
        "noofbath": 3,
        "sft": 2200,
        "pricepermonth": 2800,
        "img": "/src/assets/9.jpg",
        "popular": false
    },
    {
        "place": "Paris",
        "id": 10,
        "flag": 2,
        "rent": true,
        "sale": false,
        "location": "Champs-Élysées",
        "buildingname": "Elegant Duplex",
        "noofroom": 5,
        "noofbed": 4,
        "noofbath": 3,
        "sft": 1800,
        "pricepermonth": 2000,
        "img": "/src/assets/10.jpg",
        "popular": true
    },
    {
        "place": "Paris",
        "id": 11,
        "flag": 2,
        "rent": true,
        "sale": false,
        "location": "Montmartre",
        "buildingname": "Artistic Loft",
        "noofroom": 3,
        "noofbed": 2,
        "noofbath": 2,
        "sft": 1000,
        "pricepermonth": 1400,
        "img": "/src/assets/11.jpg",
        "popular": false
    },
    {
        "place": "Paris",
        "id": 12,
        "flag": 2,
        "rent": true,
        "sale": false,
        "location": "Le Marais",
        "buildingname": "Historic Townhouse",
        "noofroom": 4,
        "noofbed": 3,
        "noofbath": 2,
        "sft": 1200,
        "pricepermonth": 1800,
        "img": "/src/assets/12.jpg",
        "popular": false
    },
    {
        "place": "Paris",
        "id": 13,
        "flag": 2,
        "rent": false,
        "sale": true,
        "location": "Eiffel Tower View",
        "buildingname": "Luxury Penthouse",
        "noofroom": 6,
        "noofbed": 4,
        "noofbath": 3,
        "sft": 2500,
        "pricepermonth": 3500,
        "img": "/src/assets/13.jpg",
        "popular": true
    },
    {
        "place": "Paris",
        "id": 14,
        "flag": 2,
        "rent": false,
        "sale": true,
        "location": "Latin Quarter",
        "buildingname": "Cozy Apartment",
        "noofroom": 2,
        "noofbed": 1,
        "noofbath": 1,
        "sft": 800,
        "pricepermonth": 1500,
        "img": "/src/assets/14.jpg",
        "popular": false
    },
    {
        "place": "Paris",
        "id": 15,
        "flag": 2,
        "rent": true,
        "sale": false,
        "location": "Louvre District",
        "buildingname": "Stylish Studio",
        "noofroom": 1,
        "noofbed": 1,
        "noofbath": 1,
        "sft": 500,
        "pricepermonth": 900,
        "img": "/src/assets/15.jpg",
        "popular": false
    },
    {
        "place": "Paris",
        "id": 16,
        "flag": 2,
        "rent": true,
        "sale": false,
        "location": "Marais District",
        "buildingname": "Charming Flat",
        "noofroom": 2,
        "noofbed": 2,
        "noofbath": 1,
        "sft": 750,
        "pricepermonth": 1100,
        "img": "/src/assets/16.jpg",
        "popular": true
    },
    {
        "place": "Paris",
        "id": 17,
        "flag": 2,
        "rent": true,
        "sale": false,
        "location": "Seine River View",
        "buildingname": "Riverside Retreat",
        "noofroom": 3,
        "noofbed": 3,
        "noofbath": 2,
        "sft": 1200,
        "pricepermonth": 1700,
        "img": "/src/assets/17.jpg",
        "popular": false
    },
    {
        "place": "Paris",
        "id": 18,
        "flag": 2,
        "rent": true,
        "sale": false,
        "location": "Bandra",
        "buildingname": "Modern Apartment",
        "noofroom": 2,
        "noofbed": 1,
        "noofbath": 1,
        "sft": 800,
        "pricepermonth": 1200,
        "img": "/src/assets/18.jpg",
        "popular": true
    },
    {
        "place": "Mumbai",
        "id": 19,
        "flag": 3,
        "rent": true,
        "sale": false,
        "location": "South Mumbai",
        "buildingname": "Luxury Penthouse",
        "noofroom": 6,
        "noofbed": 5,
        "noofbath": 4,
        "sft": 2500,
        "pricepermonth": 3500,
        "img": "/src/assets/19.jpg",
        "popular": false
    },
    {
        "place": "Mumbai",
        "id": 20,
        "flag": 3,
        "rent": true,
        "sale": false,
        "location": "Andheri",
        "buildingname": "Spacious Villa",
        "noofroom": 7,
        "noofbed": 4,
        "noofbath": 3,
        "sft": 3000,
        "pricepermonth": 2800,
        "img": "/src/assets/20.jpg",
        "popular": false
    },
    {
        "place": "Mumbai",
        "id": 21,
        "flag": 3,
        "rent": false,
        "sale": true,
        "location": "Malabar Hill",
        "buildingname": "Sea View Mansion",
        "noofroom": 5,
        "noofbed": 3,
        "noofbath": 3,
        "sft": 2200,
        "pricepermonth": 4000,
        "img": "/src/assets/21.jpg",
        "popular": true
    },
    {
        "place": "Mumbai",
        "id": 22,
        "flag": 3,
        "rent": false,
        "sale": true,
        "location": "Powai",
        "buildingname": "Lakefront Condo",
        "noofroom": 3,
        "noofbed": 2,
        "noofbath": 2,
        "sft": 1100,
        "pricepermonth": 1800,
        "img": "/src/assets/22.jpg",
        "popular": false
    },
    {
        "place": "Mumbai",
        "id": 23,
        "flag": 3,
        "rent": true,
        "sale": false,
        "location": "Colaba",
        "buildingname": "Art Deco Flat",
        "noofroom": 2,
        "noofbed": 1,
        "noofbath": 1,
        "sft": 700,
        "pricepermonth": 1200,
        "img": "/src/assets/23.jpg",
        "popular": false
    },
    {
        "place": "Mumbai",
        "id": 24,
        "flag": 3,
        "rent": true,
        "sale": false,
        "location": "Juhu Beach",
        "buildingname": "Beachfront Bungalow",
        "noofroom": 8,
        "noofbed": 5,
        "noofbath": 4,
        "sft": 3500,
        "pricepermonth": 6000,
        "img": "/src/assets/24.jpg",
        "popular": true
    },
    {
        "place": "Mumbai",
        "id": 25,
        "flag": 3,
        "rent": true,
        "sale": false,
        "location": "Manhattan",
        "buildingname": "High-Rise Condo",
        "noofroom": 3,
        "noofbed": 2,
        "noofbath": 2,
        "sft": 1200,
        "pricepermonth": 2200,
        "img": "/src/assets/25.jpg",
        "popular": true
    },
    {
        "place": "Mumbai",
        "id": 26,
        "flag": 3,
        "rent": true,
        "sale": false,
        "location": "Brooklyn",
        "buildingname": "Brownstone Townhouse",
        "noofroom": 4,
        "noofbed": 3,
        "noofbath": 2,
        "sft": 1400,
        "pricepermonth": 1800,
        "img": "/src/assets/26.jpg",
        "popular": false
    },
    {
        "place": "Mumbai",
        "id": 27,
        "flag": 3,
        "rent": true,
        "sale": false,
        "location": "Queens",
        "buildingname": "Cozy Apartment",
        "noofroom": 2,
        "noofbed": 1,
        "noofbath": 1,
        "sft": 800,
        "pricepermonth": 1500,
        "img": "/src/assets/27.jpg",
        "popular": false
    },
    {
        "place": "New York",
        "id": 28,
        "flag": 4,
        "rent": false,
        "sale": true,
        "location": "Harlem",
        "buildingname": "Classic Brownstone",
        "noofroom": 6,
        "noofbed": 4,
        "noofbath": 3,
        "sft": 2000,
        "pricepermonth": 3200,
        "img": "/src/assets/28.jpg",
        "popular": true
    },
    {
        "place": "New York",
        "id": 29,
        "flag": 4,
        "rent": false,
        "sale": true,
        "location": "Upper West Side",
        "buildingname": "Luxury Penthouse",
        "noofroom": 5,
        "noofbed": 4,
        "noofbath": 3,
        "sft": 1800,
        "pricepermonth": 2800,
        "img": "/src/assets/29.jpg",
        "popular": false
    },
    {
        "place": "New York",
        "id": 30,
        "flag": 4,
        "rent": true,
        "sale": false,
        "location": "Greenwich Village",
        "buildingname": "Bohemian Loft",
        "noofroom": 2,
        "noofbed": 1,
        "noofbath": 1,
        "sft": 900,
        "pricepermonth": 1600,
        "img": "/src/assets/30.jpg",
        "popular": false
    },
    {
        "place": "New York",
        "id": 31,
        "flag": 4,
        "rent": true,
        "sale": false,
        "location": "Financial District",
        "buildingname": "Modern Condo",
        "noofroom": 3,
        "noofbed": 2,
        "noofbath": 2,
        "sft": 1100,
        "pricepermonth": 2000,
        "img": "/src/assets/31.jpg",
        "popular": true
    },
    {
        "place": "New York",
        "id": 32,
        "flag": 4,
        "rent": false,
        "sale": true,
        "location": "Chelsea",
        "buildingname": "Artistic Loft",
        "noofroom": 2,
        "noofbed": 1,
        "noofbath": 1,
        "sft": 800,
        "pricepermonth": 1500,
        "img": "/src/assets/32.jpg",
        "popular": false
    },
    {
        "place": "New York",
        "id": 33,
        "flag": 4,
        "rent": false,
        "sale": true,
        "location": "East Village",
        "buildingname": "Cozy Apartment",
        "noofroom": 1,
        "noofbed": 1,
        "noofbath": 1,
        "sft": 500,
        "pricepermonth": 900,
        "img": "/src/assets/33.jpg",
        "popular": true
    },
    {
        "place": "New York",
        "id": 34,
        "flag": 4,
        "rent": true,
        "sale": false,
        "location": "Upper East Side",
        "buildingname": "Luxury Penthouse",
        "noofroom": 4,
        "noofbed": 3,
        "noofbath": 3,
        "sft": 1600,
        "pricepermonth": 2800,
        "img": "/src/assets/34.jpg",
        "popular": false
    },
    {
        "place": "New York",
        "id": 35,
        "flag": 4,
        "rent": true,
        "sale": false,
        "location": "Williamsburg",
        "buildingname": "Charming Brownstone",
        "noofroom": 5,
        "noofbed": 4,
        "noofbath": 2,
        "sft": 2000,
        "pricepermonth": 2300,
        "img": "/src/assets/35.jpg",
        "popular": true
    },
    {
        "place": "New York",
        "id": 36,
        "flag": 4,
        "rent": false,
        "sale": true,
        "location": "DUMBO",
        "buildingname": "Riverside Loft",
        "noofroom": 2,
        "noofbed": 2,
        "noofbath": 2,
        "sft": 1200,
        "pricepermonth": 2200,
        "img": "/src/assets/36.jpg",
        "popular": false
    }
]